UART/UART_TX/MUX4x1.v
module MUX4x1 (
    input  wire       Ser_Data, // Serial Data Input
    input  wire       Par_Bit,  // Parity Bit Input         
    input  wire [1:0] SEL,      // 2-bit select input
    output reg        OUT       // Output
);
    always @(*) begin
        case (SEL)
            2'b00: OUT = 1'b0;
            2'b01: OUT = 1'b1;
            2'b10: OUT = Ser_Data;
            2'b11: OUT = Par_Bit;
            default: OUT = 1'b1; // Default case (should not occur)
        endcase
    end
endmodule

UART/UART_TX/Parity_Calc.v
module Parity_Calc(
    input  wire       clk,
    input  wire       rst_n,
    input  wire [7:0] P_DATA,
    input  wire       Capture,
    input  wire       Par_Type, // 0: Even, 1: Odd
    output reg        parity_out
);

    reg [7:0] data_reg;

    // Parity Calculator
    always @(posedge clk or negedge rst_n) begin
        if (!rst_n) begin
            parity_out <= 1'b0;
            data_reg <= 8'b0;
        end
        else if (Capture) begin
            data_reg <= P_DATA;
        end
        else begin
            if (Par_Type) // Odd Parity
                parity_out <= ~^data_reg;
            else          // Even Parity
                parity_out <= ^data_reg;
        end
    end
endmodule

UART/UART_TX/Serializer.v
module Serializer(
    input  wire       clk,
    input  wire       rst_n,
    input  wire [7:0] P_DATA,
    input  wire       Ser_En,
    output reg        Ser_Data,
    output reg        Ser_Done
);

    reg [7:0] data_reg;
    reg [2:0] bit_count;

    always @(posedge clk or negedge rst_n) begin
        if (!rst_n) begin
            Ser_Data  <= 1'b0;
            Ser_Done  <= 1'b0;
            bit_count <= 3'b0;
            data_reg  <= 8'b0;
        end else if (Ser_En) begin
            // Serialization logic
            Ser_Data <= data_reg[bit_count];
            if (&bit_count) begin // All bits sent  
                Ser_Done <= 1'b1;
            end
            bit_count <= bit_count + 1;
        end else begin
            data_reg <= P_DATA;
            Ser_Done <= 1'b0;
            bit_count <= 3'b0;
        end
    end

endmodule

UART/UART_TX/FSM.v
module FSM(
    input  wire       clk,
    input  wire       rst_n,
    input  wire       Data_Valid,
    input  wire       Ser_Done,
    input  wire       Par_En,
    output reg [1:0]  MUX_SEL,
    output reg        Ser_En,
    output reg        Busy,
    output reg        Capture
);

    // State Encoding
    localparam [1:0] IDLE      = 3'b000,
                     START_BIT = 3'b001,
                     DATA_BITS = 3'b011,
                     PARITY_BIT= 3'b010,
                     STOP_BIT  = 3'b110;

    reg [2:0] current_state, next_state;

    // State Transition
    always @(posedge clk or negedge rst_n) begin
        if (!rst_n)
            current_state <= IDLE;
        else
            current_state <= next_state;
    end

    // Next State Logic
    always @(*) begin
        Capture = 1'b0;
        case (current_state)
            IDLE: begin
                if (Data_Valid) begin
                    next_state = START_BIT;
                    Capture = 1'b1; // Capture data when transitioning from IDLE
                end
                else
                    next_state = IDLE;
            end
            START_BIT: next_state = DATA_BITS;
            DATA_BITS: begin
                if (Ser_Done) begin
                    if (Par_En)
                        next_state = PARITY_BIT;
                    else
                        next_state = STOP_BIT;
                end
                else
                    next_state = DATA_BITS;
            end
            PARITY_BIT: begin
                next_state = STOP_BIT;
            end
            STOP_BIT: begin
                if (Data_Valid) begin
                    next_state = START_BIT;
                    Capture = 1'b1; // Capture data 
                end
                else
                    next_state = IDLE;
            end
            default: next_state = IDLE;
        endcase
    end

    // Output Logic
    always @(*) begin
        // Default values for outputs
        Ser_En   = 1'b0;
        Busy     = 1'b1; // Assume busy unless in IDLE

        case (current_state)
            START_BIT: begin
                MUX_SEL = 2'b00; // Start bit (0)
                Ser_En = 1'b1; // Enable Serializer
            end
            DATA_BITS: begin
                MUX_SEL = 2'b10; // Data bits from Serializer
                Ser_En = 1'b1; // Keep Serializer enabled
            end
            PARITY_BIT: begin
                MUX_SEL = 2'b11; // Parity bit from Parity Calculator
            end
            STOP_BIT: begin
                MUX_SEL = 2'b01; // Stop bit (1)
            end     
            default: begin
                MUX_SEL = 2'b01; // Default to stop bit (0)
                Busy = 1'b0; // Not busy in IDLE
            end
        endcase
    end
endmodule

UART/UART_TX/UART_TX.v
module UART_TX(
    input wire        clk,
    input wire        rst_n,
    input wire [7:0]  P_DATA,
    input wire        Data_Valid,
    input wire        Par_En,
    input wire        Par_Typ, // 0: Even, 1: Odd
    output wire       TX_OUT,
    output wire       Busy
);

    wire [1:0] mux_sel;
    wire       ser_en, ser_done, capture, s_data, parity;

    FSM U0 (
        .clk(clk),
        .rst_n(rst_n),
        .Data_Valid(Data_Valid),
        .Ser_Done(ser_done),
        .Par_En(Par_En),
        .MUX_SEL(mux_sel),
        .Ser_En(ser_en),
        .Busy(Busy),
        .Capture(capture)
    );

    Serializer U1 (
        .clk(clk),
        .rst_n(rst_n),
        .P_DATA(P_DATA),
        .Ser_En(ser_en),
        .Ser_Data(s_data),
        .Ser_Done(ser_done)
    );

    Parity_Calc U2 (
        .clk(clk),
        .rst_n(rst_n),
        .P_DATA(P_DATA),
        .Capture(capture),
        .Par_Type(Par_Typ),
        .parity_out(parity)
    );

    MUX4x1 U3 (
        .Ser_Data(s_data),
        .Par_Bit(parity),
        .SEL(mux_sel),
        .OUT(TX_OUT)
    );

endmodule

UART/UART_TX/UART_TX_tb.v
`timescale 1ns/1ps
module UART_TX_tb();

    /////////////////////////////////////////////////////////
    ///////////////////// Parameters ////////////////////////
    /////////////////////////////////////////////////////////

    parameter CLOCK_PERIOD = 5; // Clock period in ns
    reg [3:0] count;
    integer correct, error;

    /////////////////////////////////////////////////////////
    /////////// Testbench Signal Declaration ////////////////
    /////////////////////////////////////////////////////////

    reg        clk_tb, rst_n_tb;
    reg [7:0]  P_DATA_tb;
    reg        Data_Valid_tb, Par_En_tb, Par_Typ_tb;
    wire       TX_OUT_tb, Busy_tb;

    reg        TX_OUT_expec, Busy_expec, Busy_expec_temp, done;
    reg [7:0]  P_DATA_reg;

    ////////////////////////////////////////////////////////
    /////////////////// DUT Instantation ///////////////////
    ////////////////////////////////////////////////////////

    UART_TX DUT (
        .clk(clk_tb),
        .rst_n(rst_n_tb),
        .P_DATA(P_DATA_tb),
        .Data_Valid(Data_Valid_tb),
        .Par_En(Par_En_tb),
        .Par_Typ(Par_Typ_tb), 
        .TX_OUT(TX_OUT_tb),
        .Busy(Busy_tb)
    );
    ////////////////////////////////////////////////////////
    ////////////////// Clock Generator  ////////////////////
    ////////////////////////////////////////////////////////

    always #(CLOCK_PERIOD/2) clk_tb = ~clk_tb;

    ////////////////////////////////////////////////////////
    /////////// Applying Stimulus on Inputs //////////////// 
    ////////////////////////////////////////////////////////

    initial begin
        // System Functions
        $dumpfile("UART_TX.vcd");
        $dumpvars;

        // initialization
        initialize();
        check_out();

        $display("Start of Odd Parity Testing at %0t", $time);
        
        repeat(50) begin
            @(negedge clk_tb);
            Data_Valid_tb = $random;
            P_DATA_tb = $random;
            Par_En_tb = 1'b1; // Parity enabled
            Par_Typ_tb = 1'b1; // Odd Parity
            if (Data_Valid_tb) 
                $display("Data Valid at time %0t with P_DATA = %b", $time, P_DATA_tb);
            // @(negedge clk_tb);
            check_out(); 
        end

        $display("Start of Even Parity Testing at %0t", $time);
                
        repeat(50) begin
            @(negedge clk_tb);
            Data_Valid_tb = $random;
            P_DATA_tb = $random;
            Par_En_tb = 1'b1; // Parity enabled
            Par_Typ_tb = 1'b0; // Even Parity
            // @(negedge clk_tb);
            if (Data_Valid_tb) 
                $display("Data Valid at time %0t with P_DATA = %b", $time, P_DATA_tb);
            check_out(); 
        end

        $display("Start of no Parity Testing at %0t", $time);
        
        repeat(25) begin
            @(negedge clk_tb);
            Data_Valid_tb = $random;
            P_DATA_tb = $random;
            Par_En_tb = 1'b0; // Parity Disabled
            Par_Typ_tb = 1'b1; // Odd Parity
            // @(negedge clk_tb);
            if (Data_Valid_tb) 
                $display("Data Valid at time %0t with P_DATA = %b", $time, P_DATA_tb);
            check_out(); 
        end

        repeat(25) begin
            @(negedge clk_tb);
            Data_Valid_tb = $random;
            P_DATA_tb = $random;
            Par_En_tb = 1'b0; // Parity Disabled
            Par_Typ_tb = 1'b0; // Even Parity
            // @(negedge clk_tb);
            if (Data_Valid_tb) 
                $display("Data Valid at time %0t with P_DATA = %b", $time, P_DATA_tb);
            check_out(); 
        end
         Data_Valid_tb = 1'b0;
        #(20*CLOCK_PERIOD)
        $display("Simulation Ended with %0d correct and %0d errors", correct, error);
        $stop;
    end

    ////////////////////////////////////////////////////////
    /////////////////////// TASKS //////////////////////////
    ////////////////////////////////////////////////////////

    /////////////// Signals Initialization //////////////////

    task initialize;
        begin
            count = 0;
            correct = 0;
            error = 0;
            done = 1'b0;
            clk_tb  	  = 1'b0;
            Data_Valid_tb = 1'b0;
            P_DATA_tb     = 8'hFF;
            Par_En_tb     = 1'b0; // Parity Disabled
            Par_Typ_tb    = 1'b0; // Even Parity
            TX_OUT_expec = 1'b1; // Assuming TX_OUT is high during reset
            Busy_expec = 1'b0; // Not busy during reset
            Busy_expec_temp = 1'b0;
            reset();
        end	
    endtask

    ///////////////////////// RESET /////////////////////////

    task reset;
        begin
            rst_n_tb = 1'b1;
            @(negedge clk_tb)
            rst_n_tb = 1'b0;
            @(negedge clk_tb)
            rst_n_tb = 1'b1;
        end
    endtask

    ////////////////// Check Out Response  ////////////////////

    task check_out;
        begin
            if(!rst_n_tb) begin
                // During Reset
                TX_OUT_expec = 1'b1; // Assuming TX_OUT is high during reset
                Busy_expec = 1'b0; // Not busy during reset
                Busy_expec_temp = 1'b0;
                P_DATA_reg = 8'b0; // Clear stored data
                count = 0; // Reset count for next transmission
                done = 1'b0; // Reset done for next transmission
            end
            else if (Data_Valid_tb && !Busy_expec) begin
                // When Data is Valid, TX_OUT should start transmitting
                P_DATA_reg = P_DATA_tb; // Store the data for calculation
                Busy_expec_temp = 1'b1; // Indicate start of transmission
            end
            else if (Busy_expec_temp) begin
                TX_OUT_expec = 1'b0; // Start bit
                if (count == 9) begin// After sending all data bits
                    if (Par_En_tb && !done) begin
                        if (Par_Typ_tb) // Odd Parity
                            TX_OUT_expec = ~^P_DATA_reg; // Calculate odd parity
                        else          // Even Parity
                            TX_OUT_expec = ^P_DATA_reg; // Calculate even parity
                        done = 1'b1; // Indicate transmission done
                    end else if (!Par_En_tb || done)  begin
                        TX_OUT_expec = 1'b1; // Stop bit
                        Busy_expec_temp = 1'b0;
                        done = 1'b0; // Reset done for next transmission
                        count = 0; // Reset count for next transmission
                        if (Data_Valid_tb) begin
                            P_DATA_reg = P_DATA_tb; // Store the data for calculation
                            Busy_expec_temp = 1'b1;
                        end
                    end
                end else if (count != 0) begin
                    TX_OUT_expec = P_DATA_reg[count-1]; // Serial state
                    count = count + 1; // Increment count for next bit
                end
                else begin
                    count = count + 1; // Increment count for next bit
                end
            end else begin
                // Idle State
                TX_OUT_expec = 1'b1; // Idle state
                Busy_expec_temp = 1'b0; // Not busy
                count = 0; // Reset count for next transmission
            end
            // Check if the outputs match the expected values
            if(TX_OUT_tb === TX_OUT_expec && Busy_tb === Busy_expec) begin
                $display("Test Case has succeeded");
                correct = correct + 1;
            end else begin
                $display("Test Case has failed at %0t", $time);
                error = error + 1;
            end
            Busy_expec = Busy_expec_temp; // Update Busy_expec for next cycle
        end
    endtask

endmodule

UART/UART_TX/UART_TX.vcd
$date
	Wed Oct 15 17:42:25 2025
$end
$version
	QuestaSim Version 2021.1
$end
$timescale
	1ps
$end

$scope module UART_TX_tb $end
$var parameter 32 ! CLOCK_PERIOD $end
$var reg 4 " count [3:0] $end
$var integer 32 # correct $end
$var integer 32 $ error $end
$var reg 1 % clk_tb $end
$var reg 1 & rst_n_tb $end
$var reg 8 ' P_DATA_tb [7:0] $end
$var reg 1 ( Data_Valid_tb $end
$var reg 1 ) Par_En_tb $end
$var reg 1 * Par_Typ_tb $end
$var wire 1 + TX_OUT_tb $end
$var wire 1 , Busy_tb $end
$var reg 1 - TX_OUT_expec $end
$var reg 1 . Busy_expec $end
$var reg 1 / Busy_expec_temp $end
$var reg 1 0 done $end
$var reg 8 1 P_DATA_reg [7:0] $end

$scope task initialize $end
$upscope $end

$scope task reset $end
$upscope $end

$scope task check_out $end
$upscope $end

$scope module DUT $end
$var wire 1 2 clk $end
$var wire 1 3 rst_n $end
$var wire 1 4 P_DATA [7] $end
$var wire 1 5 P_DATA [6] $end
$var wire 1 6 P_DATA [5] $end
$var wire 1 7 P_DATA [4] $end
$var wire 1 8 P_DATA [3] $end
$var wire 1 9 P_DATA [2] $end
$var wire 1 : P_DATA [1] $end
$var wire 1 ; P_DATA [0] $end
$var wire 1 < Data_Valid $end
$var wire 1 = Par_En $end
$var wire 1 > Par_Typ $end
$var wire 1 + TX_OUT $end
$var wire 1 , Busy $end
$var wire 1 ? mux_sel [1] $end
$var wire 1 @ mux_sel [0] $end
$var wire 1 A ser_en $end
$var wire 1 B ser_done $end
$var wire 1 C capture $end
$var wire 1 D s_data $end
$var wire 1 E parity $end

$scope module U0 $end
$var parameter 3 F IDLE $end
$var parameter 3 G START_BIT $end
$var parameter 3 H DATA_BITS $end
$var parameter 3 I PARITY_BIT $end
$var parameter 3 J STOP_BIT $end
$var wire 1 2 clk $end
$var wire 1 3 rst_n $end
$var wire 1 < Data_Valid $end
$var wire 1 B Ser_Done $end
$var wire 1 = Par_En $end
$var reg 2 K MUX_SEL [1:0] $end
$var reg 1 L Ser_En $end
$var reg 1 M Busy $end
$var reg 1 N Capture $end
$var reg 3 O current_state [2:0] $end
$var reg 3 P next_state [2:0] $end
$upscope $end

$scope module U1 $end
$var wire 1 2 clk $end
$var wire 1 3 rst_n $end
$var wire 1 4 P_DATA [7] $end
$var wire 1 5 P_DATA [6] $end
$var wire 1 6 P_DATA [5] $end
$var wire 1 7 P_DATA [4] $end
$var wire 1 8 P_DATA [3] $end
$var wire 1 9 P_DATA [2] $end
$var wire 1 : P_DATA [1] $end
$var wire 1 ; P_DATA [0] $end
$var wire 1 A Ser_En $end
$var reg 1 Q Ser_Data $end
$var reg 1 R Ser_Done $end
$var reg 8 S data_reg [7:0] $end
$var reg 3 T bit_count [2:0] $end
$upscope $end

$scope module U2 $end
$var wire 1 2 clk $end
$var wire 1 3 rst_n $end
$var wire 1 4 P_DATA [7] $end
$var wire 1 5 P_DATA [6] $end
$var wire 1 6 P_DATA [5] $end
$var wire 1 7 P_DATA [4] $end
$var wire 1 8 P_DATA [3] $end
$var wire 1 9 P_DATA [2] $end
$var wire 1 : P_DATA [1] $end
$var wire 1 ; P_DATA [0] $end
$var wire 1 C Capture $end
$var wire 1 > Par_Type $end
$var reg 1 U parity_out $end
$var reg 8 V data_reg [7:0] $end
$upscope $end

$scope module U3 $end
$var wire 1 D Ser_Data $end
$var wire 1 E Par_Bit $end
$var wire 1 ? SEL [1] $end
$var wire 1 @ SEL [0] $end
$var reg 1 W OUT $end
$upscope $end
$upscope $end
$upscope $end
$enddefinitions $end
#0
$dumpvars
b0 "
0%
1&
b11111111 '
0(
0)
0*
1-
0.
0/
00
bx 1
bx K
xL
xM
0N
bx O
b0 P
xQ
xR
bx S
bx T
xU
bx V
xW
b101 !
b0 F
b1 G
b11 H
b10 I
b110 J
b0 #
b0 $
x+
x,
x@
x?
xA
xB
0C
xD
xE
0>
0=
0<
1;
1:
19
18
17
16
15
14
13
02
$end
#2000
1%
12
b0 O
b11111111 S
0R
b0 T
0B
0L
1M
b1 K
0M
0A
0,
1@
0?
1W
1+
#4000
0%
02
0&
03
0Q
b0 S
0U
b0 V
0D
0E
#6000
1%
12
#8000
0%
02
1&
b1 #
13
#10000
1%
12
b11111111 S
#12000
0%
02
b10000001 '
1)
1*
b10 #
0:
09
08
07
06
05
1>
1=
#14000
1%
12
1U
b10000001 S
1E
#16000
0%
02
1(
b1100011 '
b1100011 1
1/
b11 #
1.
1:
16
15
04
1<
b1 P
1N
1C
#18000
1%
12
b1 O
b1100011 S
b1100011 V
0N
b11 P
1M
b0 K
1L
0C
1,
1A
0@
0W
0+
#20000
0%
02
b10001101 '
0-
b1 "
b100 #
0:
19
18
06
05
14
#22000
1%
12
1Q
b1 T
b11 O
1D
0L
b10 K
1L
1?
1W
1+
#24000
0%
02
b10010 '
1-
b10 "
b101 #
0;
1:
09
08
17
04
#26000
1%
12
b10 T
#28000
0%
02
b1101 '
0-
1-
b11 "
b110 #
1;
0:
19
18
07
#30000
1%
12
0Q
b11 T
0D
0W
0+
#32000
0%
02
0(
b111101 '
0-
b100 "
b111 #
17
16
0<
#34000
1%
12
b100 T
#36000
0%
02
1(
b10001100 '
b101 "
b1000 #
0;
07
06
14
1<
#38000
1%
12
b101 T
#40000
0%
02
b11000110 '
b110 "
b1001 #
1:
08
15
#42000
1%
12
1Q
b110 T
1D
1W
1+
#44000
0%
02
b10101010 '
1-
b111 "
b1010 #
09
18
16
05
#46000
1%
12
b111 T
#48000
0%
02
b1110111 '
0-
1-
b1000 "
b1011 #
1;
19
08
17
15
04
#50000
1%
12
0Q
1R
b0 T
0D
1B
b10 P
0W
0+
#52000
0%
02
0(
b10001111 '
0-
b1001 "
b1100 #
18
07
06
05
14
0<
#54000
1%
12
b10 O
1Q
b1 T
1D
1W
b110 P
0L
b11 K
1+
0A
1@
#56000
0%
02
b11001110 '
1-
10
b1101 #
0;
15
#58000
1%
12
b11001110 S
0R
b0 T
b110 O
0B
b0 P
b1 K
0?
#60000
0%
02
b11000101 '
0-
1-
0/
00
b0 "
b1110 #
0.
1;
0:
08
#62000
1%
12
b0 O
b11000101 S
0M
0,
#64000
0%
02
b10111101 '
b1111 #
18
17
16
05
#66000
1%
12
b10111101 S
#68000
0%
02
1(
b1100101 '
b1100101 1
1/
b10000 #
1.
08
07
15
04
1<
b1 P
1N
1C
#70000
1%
12
b1 O
b1100101 V
b1100101 S
0N
b11 P
1M
b0 K
1L
0C
1,
1A
0@
0W
0+
#72000
0%
02
b1010 '
0-
b1 "
b10001 #
0;
1:
09
18
06
05
#74000
1%
12
b1 T
b11 O
0L
b10 K
1L
1?
1W
1+
#76000
0%
02
0(
b100000 '
1-
b10 "
b10010 #
0:
08
16
0<
#78000
1%
12
0Q
b10 T
0D
0W
0+
#80000
0%
02
b10011101 '
0-
b11 "
b10011 #
1;
19
18
17
06
14
#82000
1%
12
1Q
b11 T
1D
1W
1+
#84000
0%
02
b10011 '
1-
b100 "
b10100 #
1:
09
08
04
#86000
1%
12
0Q
b100 T
0D
0W
0+
#88000
0%
02
1(
b1010011 '
0-
b101 "
b10101 #
15
1<
#90000
1%
12
b101 T
#92000
0%
02
b11010101 '
b110 "
b10110 #
0:
19
14
#94000
1%
12
1Q
b110 T
1D
1W
1+
#96000
0%
02
0(
b10101110 '
1-
b111 "
b10111 #
0;
1:
18
07
16
05
0<
#98000
1%
12
b111 T
#100000
0%
02
1(
b11001111 '
0-
1-
b1000 "
b11000 #
1;
06
15
1<
#102000
1%
12
0Q
1R
b0 T
0D
1B
b10 P
0W
0+
#104000
0%
02
b1010 '
0-
b1001 "
b11001 #
0;
09
05
04
#106000
1%
12
b10 O
1Q
b1 T
1D
1W
b110 P
0L
b11 K
1+
0A
1@
#108000
0%
02
0(
b111100 '
1-
10
b11010 #
0:
19
17
16
0<
#110000
1%
12
b111100 S
0R
b0 T
b110 O
0B
b0 P
b1 K
0?
#112000
0%
02
b10001010 '
0-
1-
0/
00
b0 "
b11011 #
0.
1:
09
07
06
14
#114000
1%
12
b0 O
b10001010 S
0M
0,
#116000
0%
02
1(
b11011000 '
b11011000 1
1/
b11100 #
1.
0:
17
15
1<
b1 P
1N
1C
#118000
1%
12
b11011000 V
b11011000 S
b1 O
0N
b11 P
1M
b0 K
1L
0C
1,
1A
0@
0W
0+
#120000
0%
02
0(
b10001001 '
0-
b1 "
b11101 #
1;
07
05
0<
#122000
1%
12
b11 O
0Q
b1 T
0D
0L
b10 K
1L
1?
#124000
0%
02
1(
b10110110 '
b10 "
b11110 #
0;
1:
19
08
17
16
1<
#126000
1%
12
b10 T
#128000
0%
02
0(
b10101110 '
b11 "
b11111 #
18
07
0<
#130000
1%
12
b11 T
#132000
0%
02
b101010 '
b100 "
b100000 #
09
04
#134000
1%
12
1Q
b100 T
1D
1W
1+
#136000
0%
02
1(
b1110001 '
1-
b101 "
b100001 #
1;
0:
08
17
15
1<
#138000
1%
12
b101 T
#140000
0%
02
b1001111 '
0-
1-
b110 "
b100010 #
1:
19
18
07
06
#142000
1%
12
0Q
b110 T
0D
0W
0+
#144000
0%
02
b111010 '
0-
b111 "
b100011 #
0;
09
17
16
05
#146000
1%
12
1Q
b111 T
1D
1W
1+
#148000
0%
02
0(
b10101 '
1-
b1000 "
b100100 #
1;
0:
19
08
06
0<
#150000
1%
12
1R
b0 T
1B
b10 P
#152000
0%
02
1(
b11011001 '
0-
1-
b1001 "
b100101 #
09
18
15
14
1<
#154000
1%
12
b10 O
0Q
b1 T
0D
0W
b110 P
0L
b11 K
0+
0A
1@
1W
1+
#156000
0%
02
0(
b1001100 '
0-
1-
10
b100110 #
0;
19
07
04
0<
#158000
1%
12
b1001100 S
0R
b0 T
b110 O
0B
b0 P
b1 K
0?
#160000
0%
02
1(
b10001111 '
0-
1-
0/
00
b0 "
b10001111 1
1/
b100111 #
1;
1:
05
14
1<
b1 P
1N
1C
#162000
1%
12
b10001111 V
b1 O
b10001111 S
0N
b11 P
b0 K
1L
0C
1A
0@
0W
0+
#164000
0%
02
0(
b10110111 '
0-
b1 "
b101000 #
08
17
16
0<
#166000
1%
12
1Q
b1 T
b11 O
0U
1D
0E
0L
b10 K
1L
1?
1W
1+
#168000
0%
02
1(
b1011100 '
1-
b10 "
b101001 #
0;
0:
18
06
15
04
1<
#170000
1%
12
b10 T
#172000
0%
02
b10001001 '
0-
1-
b11 "
b101010 #
1;
09
07
05
14
#174000
1%
12
b11 T
#176000
0%
02
b11010000 '
0-
1-
b100 "
b101011 #
0;
08
17
15
#178000
1%
12
b100 T
#180000
0%
02
b1010001 '
0-
1-
b101 "
b101100 #
1;
04
#182000
1%
12
0Q
b101 T
0D
0W
0+
#184000
0%
02
0(
b1100 '
0-
b110 "
b101101 #
0;
19
18
07
05
0<
#186000
1%
12
b110 T
#188000
0%
02
b11001000 '
b111 "
b101110 #
09
15
14
#190000
1%
12
b111 T
#192000
0%
02
1(
b111101 '
b1000 "
b101111 #
1;
19
17
16
05
04
1<
#194000
1%
12
1Q
1R
b0 T
1D
1B
b10 P
1W
1+
#196000
0%
02
0(
b1111110 '
1-
b1001 "
b110000 #
0;
1:
15
0<
#198000
1%
12
b10 O
b1 T
b110 P
0L
b11 K
0A
1@
0W
0+
#200000
0%
02
1(
b111001 '
0-
10
b110001 #
1;
0:
09
05
1<
#202000
1%
12
b111001 S
0R
b0 T
b110 O
0B
b1 P
1N
b1 K
1C
0?
1W
1+
#204000
0%
02
b11010011 '
1-
0/
00
b0 "
b11010011 1
1/
b110010 #
1:
08
06
15
14
#206000
1%
12
b11010011 V
b1 O
b11010011 S
0N
b11 P
b0 K
1L
0C
1A
0@
0W
0+
#208000
0%
02
b1111000 '
0-
b1 "
b110011 #
0;
0:
18
16
04
#210000
1%
12
b1 T
b11 O
0L
b10 K
1L
1?
1W
1+
#212000
0%
02
b1001001 '
0*
1-
b10 "
b110100 #
1;
07
06
0>
#214000
1%
12
1U
b10 T
1E
#216000
0%
02
b101010 '
0-
1-
b11 "
b110101 #
0;
1:
16
05
#218000
1%
12
0Q
b11 T
0D
0W
0+
#220000
0%
02
0(
b10000110 '
0-
b100 "
b110110 #
19
08
06
14
0<
#222000
1%
12
b100 T
#224000
0%
02
b10011100 '
b101 "
b110111 #
0:
18
17
#226000
1%
12
1Q
b101 T
1D
1W
1+
#228000
0%
02
b100110 '
1-
b110 "
b111000 #
1:
08
07
16
04
#230000
1%
12
0Q
b110 T
0D
0W
0+
#232000
0%
02
1(
b10100011 '
0-
b111 "
b111001 #
1;
09
14
1<
#234000
1%
12
1Q
b111 T
1D
1W
1+
#236000
0%
02
b10110011 '
1-
b1000 "
b111010 #
17
#238000
1%
12
1R
b0 T
1B
b10 P
#240000
0%
02
b1000100 '
0-
1-
b1001 "
b111011 #
0;
0:
19
07
06
15
04
#242000
1%
12
b10 O
b1 T
b110 P
0L
b11 K
0A
1@
#244000
0%
02
b11001011 '
0-
1-
10
b111100 #
1;
1:
09
18
14
#246000
1%
12
b11001011 S
0R
b0 T
b110 O
0B
b1 P
1N
b1 K
1C
0?
#248000
0%
02
0(
b1011010 '
0-
1-
0/
00
b0 "
b111101 #
0.
0;
17
04
0<
0N
b0 P
0C
#250000
1%
12
b0 O
b1011010 S
0M
0,
#252000
0%
02
1(
b11101101 '
b11101101 1
1/
b111110 #
1.
1;
0:
19
07
16
14
1<
b1 P
1N
1C
#254000
1%
12
b11101101 V
b11101101 S
b1 O
0N
b11 P
1M
b0 K
1L
0C
1,
1A
0@
0W
0+
#256000
0%
02
0(
b1100101 '
0-
b1 "
b111111 #
08
04
0<
#258000
1%
12
b11 O
b1 T
0U
0E
0L
b10 K
1L
1?
1W
1+
#260000
0%
02
1(
b11011111 '
1-
b10 "
b1000000 #
1:
18
17
06
14
1<
#262000
1%
12
0Q
b10 T
0D
0W
0+
#264000
0%
02
b1000100 '
0-
b11 "
b1000001 #
0;
0:
08
07
04
#266000
1%
12
1Q
b11 T
1D
1W
1+
#268000
0%
02
0(
b101010 '
1-
b100 "
b1000010 #
1:
09
18
16
05
0<
#270000
1%
12
b100 T
#272000
0%
02
1(
b1110 '
0-
1-
b101 "
b1000011 #
19
06
1<
#274000
1%
12
0Q
b101 T
0D
0W
0+
#276000
0%
02
0(
b10011010 '
0-
b110 "
b1000100 #
09
17
14
0<
#278000
1%
12
1Q
b110 T
1D
1W
1+
#280000
0%
02
1(
b11000011 '
1-
b111 "
b1000101 #
1;
08
07
15
1<
#282000
1%
12
b111 T
#284000
0%
02
0(
b1001110 '
0-
1-
b1000 "
b1000110 #
0;
19
18
04
0<
#286000
1%
12
1R
b0 T
1B
b10 P
#288000
0%
02
1(
b1010 '
0-
1-
b1001 "
b1000111 #
09
05
1<
#290000
1%
12
b10 O
b1 T
b110 P
0L
b11 K
0A
1@
0W
0+
#292000
0%
02
0(
b111000 '
0-
10
b1001000 #
0:
17
16
0<
#294000
1%
12
b111000 S
0R
b0 T
b110 O
0B
b0 P
b1 K
0?
1W
1+
#296000
0%
02
1(
b10111000 '
1-
0/
00
b0 "
b10111000 1
1/
b1001001 #
14
1<
b1 P
1N
1C
#298000
1%
12
b10111000 V
b1 O
b10111000 S
0N
b11 P
b0 K
1L
0C
1A
0@
0W
0+
#300000
0%
02
0(
b10010011 '
0-
b1 "
b1001010 #
1;
1:
08
06
0<
#302000
1%
12
0Q
b1 T
b11 O
0D
0L
b10 K
1L
1?
#304000
0%
02
b1011001 '
b10 "
b1001011 #
0:
18
15
04
#306000
1%
12
b10 T
#308000
0%
02
1(
b1001101 '
b11 "
b1001100 #
19
07
1<
#310000
1%
12
b11 T
#312000
0%
02
b1101101 '
b100 "
b1001101 #
16
#314000
1%
12
1Q
b100 T
1D
1W
1+
#316000
0%
02
0(
b11001010 '
1-
b101 "
b1001110 #
0;
1:
09
06
14
0<
#318000
1%
12
b101 T
#320000
0%
02
b10010101 '
0-
1-
b110 "
b1001111 #
1;
0:
19
08
17
05
#322000
1%
12
b110 T
#324000
0%
02
b100 '
0-
1-
b111 "
b1010000 #
0;
07
04
#326000
1%
12
0Q
b111 T
0D
0W
0+
#328000
0%
02
1(
b1101001 '
0-
b1000 "
b1010001 #
1;
09
18
16
15
1<
#330000
1%
12
1Q
1R
b0 T
1D
1B
b10 P
1W
1+
#332000
0%
02
0(
b10001000 '
1-
b1001 "
b1010010 #
0;
06
05
14
0<
#334000
1%
12
b10 O
0Q
b1 T
0D
0W
b110 P
0L
b11 K
0+
0A
1@
#336000
0%
02
b101101 '
0-
10
b1010011 #
1;
19
16
04
#338000
1%
12
b101101 S
0R
b0 T
b110 O
0B
b0 P
b1 K
0?
1W
1+
#340000
0%
02
1(
b101110 '
1-
0/
00
b0 "
b101110 1
1/
b1010100 #
0;
1:
1<
b1 P
1N
1C
#342000
1%
12
b101110 V
b1 O
b101110 S
0N
b11 P
b0 K
1L
0C
1A
0@
0W
0+
#344000
0%
02
0(
b11100 '
0-
b1 "
b1010101 #
0:
17
06
0<
#346000
1%
12
b1 T
b11 O
0L
b10 K
1L
1?
#348000
0%
02
1(
b101001 '
b10 "
b1010110 #
1;
09
07
16
1<
#350000
1%
12
1Q
b10 T
1D
1W
1+
#352000
0%
02
0(
b10000110 '
1-
b11 "
b1010111 #
0;
1:
19
08
06
14
0<
#354000
1%
12
b11 T
#356000
0%
02
b111101 '
0-
1-
b100 "
b1011000 #
1;
0:
18
17
16
04
#358000
1%
12
b100 T
#360000
0%
02
b1110000 '
0-
1-
b101 "
b1011001 #
0;
09
08
15
#362000
1%
12
0Q
b101 T
0D
0W
0+
#364000
0%
02
1(
b10111010 '
0-
b110 "
b1011010 #
1:
18
05
14
1<
#366000
1%
12
1Q
b110 T
1D
1W
1+
#368000
0%
02
0(
b11111010 '
1-
b111 "
b1011011 #
15
0<
#370000
1%
12
0Q
b111 T
0D
0W
0+
#372000
0%
02
1(
b11010 '
0-
b1000 "
b1011100 #
06
05
04
1<
#374000
1%
12
1R
b0 T
1B
b10 P
#376000
0%
02
b110111 '
b1001 "
b1011101 #
1;
19
08
16
#378000
1%
12
b10 O
b1 T
b110 P
0L
b11 K
0A
1@
#380000
0%
02
0(
b11000000 '
10
b1011110 #
0;
0:
09
07
06
15
14
0<
#382000
1%
12
b11000000 S
0R
b0 T
b110 O
0B
b0 P
b1 K
0?
1W
1+
#384000
0%
02
b10110110 '
1-
0/
00
b0 "
b1011111 #
0.
1:
19
17
16
05
#386000
1%
12
b0 O
b10110110 S
0M
0,
